{"is_source_file": true, "format": "JavaScript (React JSX)", "description": "React functional component for a Quiz page that loads questions, manages user answers, grades the quiz, and provides feedback, integrating with authentication, content data, and progress context.", "external_files": ["../state/AuthContext", "../data/content", "../data/quizzes", "../state/ProgressContext", "react", "react-router-dom"], "external_methods": ["useAuth", "useProgress", "useParams", "Link"], "published": [], "classes": [], "methods": [{"name": "Quiz()", "description": "Main React component rendering the quiz interface, handling user interactions, grading, and navigation.", "scope": "", "scopeKind": ""}], "calls": ["useParams", "useAuth", "useProgress", "useMemo", "useState", "recordQuizScore", "find", "setAnswers", "setSubmitted", "setResult", "grade", "onSelect"], "search-terms": ["Quiz", "React", "useParams", "useAuth", "QUIZ_CONTENT", "MODULES", "ProgressContext", "questions", "grading", "student answers"], "state": 2, "file_id": 24, "knowledge_revision": 68, "git_revision": "147db80591a8817c45897f524e851de8b6d177bd", "revision_history": [{"53": ""}, {"68": "147db80591a8817c45897f524e851de8b6d177bd"}], "ctags": [{"_type": "tag", "name": "Quiz", "path": "/home/kavia/workspace/code-generation/learnbridge-offline-education-platform-159970-159979/app_frontend/src/pages/Quiz.js", "pattern": "/^export default function Quiz() {$/", "language": "JavaScript", "kind": "function", "signature": "()"}], "hash": "25b32fdc708d1859410003fdf4c750af", "format-version": 4, "code-base-name": "app_frontend", "filename": "app_frontend/src/pages/Quiz.js"}