{"is_source_file": true, "format": "JavaScript (React JSX)", "description": "This is a React component file for the Dashboard page of a learning platform. It displays user KPIs such as progress percentage, total points, lessons completed, and quizzes taken, along with a list of modules for continued learning.", "external_files": ["../state/AuthContext", "../state/LanguageContext", "../state/ProgressContext", "../data/content", "../components/ModuleCard"], "external_methods": ["useAuth", "useLanguage", "useProgress", "MODULES"], "published": ["Dashboard"], "classes": [], "methods": [{"name": "Dashboard()", "description": "React functional component that renders the user dashboard with KPIs and module list.", "scope": "", "scopeKind": ""}], "calls": ["useAuth()", "useLanguage()", "useProgress()", "Object.values(progress)", "Object.values(mod.lessons || {})", "Object.keys(mod.quizzes || {})", "t('yourProgress')", "t('continueLearning')", "ModuleCard"], "search-terms": ["Dashboard", "KPIs", "Content modules", "Progress calculation", "React component"], "state": 2, "file_id": 21, "knowledge_revision": 69, "git_revision": "147db80591a8817c45897f524e851de8b6d177bd", "revision_history": [{"47": ""}, {"69": "147db80591a8817c45897f524e851de8b6d177bd"}], "ctags": [{"_type": "tag", "name": "Dashboard", "path": "/home/kavia/workspace/code-generation/learnbridge-offline-education-platform-159970-159979/app_frontend/src/pages/Dashboard.js", "pattern": "/^export default function Dashboard() {$/", "language": "JavaScript", "kind": "function", "signature": "()"}], "hash": "70165897567f6200e305deaf143816aa", "format-version": 4, "code-base-name": "app_frontend", "filename": "app_frontend/src/pages/Dashboard.js"}