{"is_source_file": true, "format": "JavaScript (React JSX)", "description": "React component 'ModuleDetail' for displaying a lesson module, quiz, and progress tracking in an educational platform.", "external_files": ["../contexts/ProgressContext", "react", "react-router-dom", "react-i18next"], "external_methods": ["useParams", "useProgress", "useTranslation", "awardPoints", "markCompleted"], "published": ["default"], "classes": [], "methods": [{"name": "ModuleDetail()", "description": "React functional component that displays lesson details, quiz, and progress, handling user interactions and updates.", "scope": "", "scopeKind": ""}, {"name": "submitAnswer", "description": "Handles quiz answer submission; awards points and provides feedback based on user choice."}, {"name": "complete", "description": "Marks the module as completed, awards bonus points, and updates feedback."}], "calls": ["useParams", "useProgress", "useTranslation", "awardPoints", "markCompleted"], "search-terms": ["React component", "ModuleDetail", "ProgressContext", "useTranslation", "quiz", "progress tracking", "lesson module"], "state": 2, "file_id": 31, "knowledge_revision": 66, "git_revision": "", "ctags": [{"_type": "tag", "name": "ModuleDetail", "path": "/home/kavia/workspace/code-generation/learnbridge-offline-education-platform-159970-159979/app_frontend/src/pages/ModuleDetail.js", "pattern": "/^export default function ModuleDetail() {$/", "language": "JavaScript", "kind": "function", "signature": "()"}], "hash": "000a63b4e9844e07b66e14bb936dc54d", "format-version": 4, "code-base-name": "app_frontend", "filename": "app_frontend/src/pages/ModuleDetail.js", "revision_history": [{"66": ""}]}