{"is_source_file": true, "format": "JavaScript", "description": "Test setup file configuring custom Jest matchers for DOM assertions using '@testing-library/jest-dom'.", "external_files": ["@testing-library/jest-dom"], "external_methods": ["expect(element).toHaveTextContent", "jest-dom matchers"], "published": [], "classes": [], "methods": [], "calls": ["import('@testing-library/jest-dom')"], "search-terms": ["jest-dom", "setupTests", "testing-library", "custom matchers"], "state": 2, "file_id": 5, "knowledge_revision": 24, "git_revision": "d87654dd6926335233a2327ab72e080cf5c4b38b", "ctags": [], "hash": "1a77571e1a8cf36018a41bcedf60db75", "format-version": 4, "code-base-name": "app_frontend", "filename": "app_frontend/src/setupTests.js", "revision_history": [{"24": "d87654dd6926335233a2327ab72e080cf5c4b38b"}]}